soil/.DS_Store
soil/__init__.py
soil/_version.py
soil/alias.py
soil/api.py
soil/configuration.py
soil/data.py
soil/data_structure.py
soil/decorator.py
soil/dictionary.py
soil/errors.py
soil/finder.py
soil/job.py
soil/logger.py
soil/modulify.py
soil/pipeline.py
soil/py.typed
soil/task.py
soil/types.py
soil/utils.py
soil/aio/__init__.py
soil/aio/alerts.py
soil/aio/alias.py
soil/aio/api.py
soil/aio/data.py
soil/aio/dictionary.py
soil/aio/job.py
soil/alerts/__init__.py
soil/alerts/alerts.py
soil/connectors/__init__.py
soil/connectors/elastic_search.py
soil/data_structures/__init__.py
soil/modules/__init__.py
soil/storage/__init__.py
soil/storage/base_storage.py
soil/storage/compound_storage.py
soil/storage/elasticsearch.py
soil/storage/object_storage.py
soil_cli/__init__.py
soil_cli/soil_cli.py
soil_sdk-0.8.19.dist-info/licenses/AUTHORS
soil_sdk-0.8.19.dist-info/METADATA
soil_sdk-0.8.19.dist-info/WHEEL
soil_sdk-0.8.19.dist-info/entry_points.txt
soil_sdk-0.8.19.dist-info/top_level.txt
soil_sdk-0.8.19.dist-info/RECORD
